mcp_codemode/__init__.py
mcp_codemode/__version__.py
mcp_codemode/models.py
mcp_codemode/server.py
mcp_codemode/toolset.py
mcp_codemode/composition/__init__.py
mcp_codemode/composition/executor.py
mcp_codemode/discovery/__init__.py
mcp_codemode/discovery/codegen.py
mcp_codemode/discovery/registry.py
mcp_codemode/proxy/__init__.py
mcp_codemode/proxy/mcp_client.py
mcp_codemode/proxy/meta_tools.py
mcp_codemode-0.0.4.dist-info/METADATA
mcp_codemode-0.0.4.dist-info/WHEEL
mcp_codemode-0.0.4.dist-info/licenses/LICENSE
mcp_codemode-0.0.4.dist-info/RECORD
