Metadata-Version: 2.4
Name: mcp_codemode
Version: 0.0.4
Project-URL: Home, https://github.com/datalayer/mcp-codemode
Author-email: Datalayer <info@datalayer.io>
License: BSD 3-Clause License
License-File: LICENSE
Keywords: AI,Jupyter,MCP,Model Context Protocol
Classifier: Intended Audience :: Developers
Classifier: Intended Audience :: System Administrators
Classifier: License :: OSI Approved :: BSD License
Classifier: Programming Language :: Python
Classifier: Programming Language :: Python :: 3
Requires-Python: >=3.10
Requires-Dist: agent-skills
Requires-Dist: code-sandboxes
Requires-Dist: httpx>=0.24
Requires-Dist: mcp[cli]>=1.0
Provides-Extra: lint
Requires-Dist: mdformat-gfm>=0.3.5; extra == 'lint'
Requires-Dist: mdformat>0.7; extra == 'lint'
Requires-Dist: ruff; extra == 'lint'
Provides-Extra: pydantic-ai
Requires-Dist: pydantic-ai-slim; extra == 'pydantic-ai'
Requires-Dist: pydantic-graph; extra == 'pydantic-ai'
Provides-Extra: test
Requires-Dist: ipykernel; extra == 'test'
Requires-Dist: jupyter-server<3,>=1.6; extra == 'test'
Requires-Dist: pytest-asyncio>=0.21; extra == 'test'
Requires-Dist: pytest>=7.0; extra == 'test'
Provides-Extra: typing
Requires-Dist: mypy>=0.990; extra == 'typing'
